{
  "experiment_name": "style_cross_market_style_global_mix",
  "candidate_config": "C:\\Users\\morph\\.codex\\worktrees\\b6cc\\strategy\\etf_selection\\generated_configs\\20260531_012414_style_cross_market_platform\\platform_style_global_mix.yaml",
  "baseline_config": "C:\\Users\\morph\\.codex\\worktrees\\b6cc\\strategy\\etf_selection\\generated_configs\\20260531_012414_style_cross_market_platform\\baseline_for_style_global_mix.yaml",
  "candidate": {
    "results_dir": "C:\\Users\\morph\\.codex\\worktrees\\b6cc\\strategy\\platform\\results\\backtests\\style_cross_market_style_global_mix\\20260531_012818\\risk_parity\\platform_style_global_mix_candidate_20260531_012818",
    "nav_csv": "C:\\Users\\morph\\.codex\\worktrees\\b6cc\\strategy\\platform\\results\\backtests\\style_cross_market_style_global_mix\\20260531_012818\\risk_parity\\platform_style_global_mix_candidate_20260531_012818\\nav.csv",
    "positions_csv": "C:\\Users\\morph\\.codex\\worktrees\\b6cc\\strategy\\platform\\results\\backtests\\style_cross_market_style_global_mix\\20260531_012818\\risk_parity\\platform_style_global_mix_candidate_20260531_012818\\positions.csv",
    "orders_csv": "C:\\Users\\morph\\.codex\\worktrees\\b6cc\\strategy\\platform\\results\\backtests\\style_cross_market_style_global_mix\\20260531_012818\\risk_parity\\platform_style_global_mix_candidate_20260531_012818\\orders.csv",
    "trades_csv": "C:\\Users\\morph\\.codex\\worktrees\\b6cc\\strategy\\platform\\results\\backtests\\style_cross_market_style_global_mix\\20260531_012818\\risk_parity\\platform_style_global_mix_candidate_20260531_012818\\trades.csv",
    "oos_metrics_available": false,
    "start_date": "2019-01-18",
    "end_date": "2026-05-19",
    "observations": 1774,
    "total_return": 0.5071509249009347,
    "annualized_return": 0.060038821934919495,
    "annualized_volatility": 0.05628664382313489,
    "max_drawdown": -0.11711535159317066,
    "sharpe_ratio": 1.066661962002474,
    "turnover_total": 2918958.799921344,
    "annualized_turnover": 414643.5273845427,
    "trade_count": 71,
    "order_count": 71,
    "filled_order_count": 71,
    "rejected_order_count": 0,
    "order_status_counts": {
      "FILLED": 71
    },
    "rejection_reason_counts": {},
    "pending_intent_count": 0,
    "max_pending_intent_count": 2,
    "average_cash_weight": 0.0375816555181347,
    "max_position_count": 7
  },
  "baseline": {
    "results_dir": "C:\\Users\\morph\\.codex\\worktrees\\b6cc\\strategy\\platform\\results\\backtests\\style_cross_market_style_global_mix\\20260531_012818\\risk_parity\\platform_baseline_for_style_global_mix_baseline_20260531_012838",
    "nav_csv": "C:\\Users\\morph\\.codex\\worktrees\\b6cc\\strategy\\platform\\results\\backtests\\style_cross_market_style_global_mix\\20260531_012818\\risk_parity\\platform_baseline_for_style_global_mix_baseline_20260531_012838\\nav.csv",
    "positions_csv": "C:\\Users\\morph\\.codex\\worktrees\\b6cc\\strategy\\platform\\results\\backtests\\style_cross_market_style_global_mix\\20260531_012818\\risk_parity\\platform_baseline_for_style_global_mix_baseline_20260531_012838\\positions.csv",
    "orders_csv": "C:\\Users\\morph\\.codex\\worktrees\\b6cc\\strategy\\platform\\results\\backtests\\style_cross_market_style_global_mix\\20260531_012818\\risk_parity\\platform_baseline_for_style_global_mix_baseline_20260531_012838\\orders.csv",
    "trades_csv": "C:\\Users\\morph\\.codex\\worktrees\\b6cc\\strategy\\platform\\results\\backtests\\style_cross_market_style_global_mix\\20260531_012818\\risk_parity\\platform_baseline_for_style_global_mix_baseline_20260531_012838\\trades.csv",
    "oos_metrics_available": false,
    "start_date": "2019-01-18",
    "end_date": "2026-05-19",
    "observations": 1774,
    "total_return": 0.5476375480664948,
    "annualized_return": 0.06404027585088334,
    "annualized_volatility": 0.034143469793905055,
    "max_drawdown": -0.03470202987878068,
    "sharpe_ratio": 1.875622959161437,
    "turnover_total": 2834049.456009494,
    "annualized_turnover": 402581.99713325396,
    "trade_count": 43,
    "order_count": 43,
    "filled_order_count": 43,
    "rejected_order_count": 0,
    "order_status_counts": {
      "FILLED": 43
    },
    "rejection_reason_counts": {},
    "pending_intent_count": 0,
    "max_pending_intent_count": 2,
    "average_cash_weight": 0.024564630459054652,
    "max_position_count": 3
  },
  "comparison": {
    "total_return_delta": -0.040486623165560065,
    "annualized_return_delta": -0.0040014539159638485,
    "annualized_volatility_delta": 0.022143174029229835,
    "max_drawdown_delta": -0.08241332171438998,
    "sharpe_ratio_delta": -0.8089609971589631,
    "annualized_turnover_delta": 12061.530251288728,
    "trade_count_delta": 28.0,
    "order_count_delta": 28.0,
    "rejected_order_count_delta": 0.0,
    "max_pending_intent_count_delta": 0.0,
    "average_cash_weight_delta": 0.013017025059080048
  },
  "generated_at": "2026-05-31T01:28:57"
}